COS_Assignment3/mod_16_counter.v
module Mod16Counter (
    input wire CLK,
    input wire RST,
    output reg [3:0] counter
);
    always @(posedge ) begin
        if (RST) begin
            counter <= 4'b0000;
        end 
        else begin
            counter <= counter + 1;
        end
    end
endmodule

COS_Assignment3/tb_mod_16_counter.v
`include "mod_16_counter.v"
module tb_Mod16Counter;
    reg CLK;
    reg RST;
    wire [3:0] counter_out;

    Mod16Counter uut (
        .CLK(CLK),
        .RST(RST),
        .counter(counter_out)
    );

    initial begin
        $dumpfile("Mod16Counter.vcd");
        $dumpvars(0, tb_Mod16Counter);
        CLK = 0;
        RST = 1;
        #10;
        RST = 0;
        #160;
        $finish;
    end

    always #5 CLK = ~CLK;
    initial begin
        $monitor("Time=%0t, CLK=%b, RST=%b, Counter=%b", $time, CLK, RST, counter_out);
    end
endmodule

COS_Assignment3/Mod16Counter.vcd
$date
	Wed Mar 13 23:06:30 2024
$end
$version
	Icarus Verilog
$end
$timescale
	1s
$end
$scope module tb_Mod16Counter $end
$var wire 4 ! counter_out [3:0] $end
$var reg 1 " CLK $end
$var reg 1 # RST $end
$scope module uut $end
$var wire 1 " CLK $end
$var wire 1 # RST $end
$var reg 4 $ counter [3:0] $end
$upscope $end
$upscope $end
$enddefinitions $end
#0
$dumpvars
bx $
1#
0"
bx !
$end
#5
b0 !
b0 $
1"
#10
0"
0#
#15
b1 !
b1 $
1"
#20
0"
#25
b10 !
b10 $
1"
#30
0"
#35
b11 !
b11 $
1"
#40
0"
#45
b100 !
b100 $
1"
#50
0"
#55
b101 !
b101 $
1"
#60
0"
#65
b110 !
b110 $
1"
#70
0"
#75
b111 !
b111 $
1"
#80
0"
#85
b1000 !
b1000 $
1"
#90
0"
#95
b1001 !
b1001 $
1"
#100
0"
#105
b1010 !
b1010 $
1"
#110
0"
#115
b1011 !
b1011 $
1"
#120
0"
#125
b1100 !
b1100 $
1"
#130
0"
#135
b1101 !
b1101 $
1"
#140
0"
#145
b1110 !
b1110 $
1"
#150
0"
#155
b1111 !
b1111 $
1"
#160
0"
#165
b0 !
b0 $
1"
