COS_Assignment3/DFF.v
module DFF(D, clk, clr, Q);

input D,clk,clr;
output reg Q;

always @(posedge clk, posedge clr)begin
    if (clr)
    Q <= 1'b0;
    else
    Q <= D;
end
endmodule

COS_Assignment3/USR.v
`include "DFF.v"
module universal_SR(clr,clk,left_in,right_in,sel,par_in,out);

input clr, clk, left_in, right_in;
input [1:0] sel;
input [3:0] par_in;

output reg [3:0]out;

wire [3:0] dff_out;
DFF dff0 (.D(right_in), .clk(clk), .clr(clr), .Q(dff_out[0]));
DFF dff1 (.D(left_in), .clk(clk), .clr(clr), .Q(dff_out[1]));
DFF dff2 (.D(par_in[0]), .clk(clk), .clr(clr), .Q(dff_out[2]));
DFF dff3 (.D(par_in[1]), .clk(clk), .clr(clr), .Q(dff_out[3]));

always @(posedge clk) begin
    if(clr)
    out = 4'b0000;
    else
    begin
    case (sel)
        2'b00: out = out; //no change
        2'b01: out = {right_in, out[3:1]}; //right shift
        2'b10: out = {out[2:0], left_in}; //left shift
        2'b11: out = par_in; //parallel shift
    endcase
    end
end

endmodule

COS_Assignment3/tb_USR.v
`include "USR.v"
module universal_SR_tst;
//Input
reg clr;
reg clk;
reg left_in;
reg right_in;
reg [3:0] par_in;
reg [1:0] sel;
//Output
wire [3:0] out;
universal_SR uut (
    .clr(clr),
    .clk(clk),
    .left_in(left_in),
    .right_in(right_in),
    .par_in(par_in),
    .sel(sel),
    .out(out)
);


initial begin
    clk = 0;
    forever #5 clk = ~clk;
end


initial begin
    clr = 1'b1;
    left_in = 1'b0;
    right_in = 1'b0;
    par_in = 4'b0000;
    sel = 2'b00;

    #10;
    
    clr = 1'b0;  
    #10;

    //perform right shift
    right_in = 1'b1;
    sel = 2'b01;
    #10;

    //perform left shift
    right_in = 1'b0;
    left_in = 1'b1;
    sel = 2'b10;
    #10;

    //perform parallel shift
    left_in = 1'b0;
    par_in = 4'b1010;
    sel = 2'b11;
    #10;

end

always @(posedge clk) begin
    $display("time=%0t, sel=%b, out=%b", $time, sel, out);
end

initial begin
    $dumpfile("test_USR.vcd");
    $dumpvars(0, universal_SR_tst);
    #60 $finish;
end
endmodule

COS_Assignment3/test_USR.vcd
$date
	Tue Mar 12 23:41:59 2024
$end
$version
	Icarus Verilog
$end
$timescale
	1s
$end
$scope module universal_SR_tst $end
$var wire 4 ! out [3:0] $end
$var reg 1 " clk $end
$var reg 1 # clr $end
$var reg 1 $ left_in $end
$var reg 4 % par_in [3:0] $end
$var reg 1 & right_in $end
$var reg 2 ' sel [1:0] $end
$scope module uut $end
$var wire 1 " clk $end
$var wire 1 # clr $end
$var wire 1 $ left_in $end
$var wire 4 ( par_in [3:0] $end
$var wire 1 & right_in $end
$var wire 2 ) sel [1:0] $end
$var wire 4 * dff_out [3:0] $end
$var reg 4 + out [3:0] $end
$scope module dff0 $end
$var wire 1 & D $end
$var wire 1 " clk $end
$var wire 1 # clr $end
$var reg 1 , Q $end
$upscope $end
$scope module dff1 $end
$var wire 1 $ D $end
$var wire 1 " clk $end
$var wire 1 # clr $end
$var reg 1 - Q $end
$upscope $end
$scope module dff2 $end
$var wire 1 . D $end
$var wire 1 " clk $end
$var wire 1 # clr $end
$var reg 1 / Q $end
$upscope $end
$scope module dff3 $end
$var wire 1 0 D $end
$var wire 1 " clk $end
$var wire 1 # clr $end
$var reg 1 1 Q $end
$upscope $end
$upscope $end
$upscope $end
$enddefinitions $end
#0
$dumpvars
01
00
0/
0.
0-
0,
bx +
b0 *
b0 )
b0 (
b0 '
0&
b0 %
0$
1#
0"
bx !
$end
#5
b0 !
b0 +
1"
#10
0"
0#
#15
1"
#20
0"
b1 '
b1 )
1&
#25
b1 *
1,
b1000 !
b1000 +
1"
#30
0"
b10 '
b10 )
1$
0&
#35
0,
b10 *
1-
b1 !
b1 +
1"
#40
10
0"
b11 '
b11 )
b1010 %
b1010 (
0$
#45
11
b1000 *
0-
b1010 !
b1010 +
1"
