COS_Assignment2/Encoder_8_to_3_SS.v
/*
This file contains Encoder for 8 to 3 bit

Author: Sahil & Shravan
Date: 08-02-2024
*/

module Encoder_8_to_3(input [7:0] A, output reg [2:0] O);

always @*
begin
    case(A)
        8'b00000001: O = 3'b000;
        8'b00000010: O = 3'b001;
        8'b00000100: O = 3'b010;
        8'b00001000: O = 3'b011;
        8'b00010000: O = 3'b100;
        8'b00100000: O = 3'b101;
        8'b01000000: O = 3'b110;
        8'b10000000: O = 3'b111;
        default: O = 3'b111; // For undefined inputs
    endcase
end

endmodule

COS_Assignment2/Encoder_8_to_3_tb_SS.v
/*
This file contains testbench code for 8 to 3 bit
Encoder

Author: Sahil & Shravan
Date: 08-02-2024
*/


`include "Encoder_8_to_3_SS.v"
module Encoder_8_to_3_tb;
reg [7:0] A_tb;
    wire [2:0] O_tb;

    Encoder_8_to_3 uut(A_tb, O_tb);

    initial begin
        $dumpfile("out.vcd");
        $dumpvars(0, Encoder_8_to_3_tb);
        
        $monitor("A=%b, O=%b", A_tb, O_tb);
        A_tb = 8'b00000001; #10;
        A_tb = 8'b00000010; #10;
        A_tb = 8'b00000100; #10;
        A_tb = 8'b00001000; #10;
        A_tb = 8'b00010000; #10;
        A_tb = 8'b00100000; #10;
        A_tb = 8'b01000000; #10;
        A_tb = 8'b10000000; #10;
        
        $finish;
    end

endmodule

COS_Assignment2/out.vcd
$date
	Fri Feb 23 14:49:38 2024
$end
$version
	Icarus Verilog
$end
$timescale
	1s
$end
$scope module Encoder_8_to_3_tb $end
$var wire 3 ! O_tb [2:0] $end
$var reg 8 " A_tb [7:0] $end
$scope module uut $end
$var wire 8 # A [7:0] $end
$var reg 3 $ O [2:0] $end
$upscope $end
$upscope $end
$enddefinitions $end
#0
$dumpvars
b0 $
b1 #
b1 "
b0 !
$end
#10
b1 !
b1 $
b10 "
b10 #
#20
b10 !
b10 $
b100 "
b100 #
#30
b11 !
b11 $
b1000 "
b1000 #
#40
b100 !
b100 $
b10000 "
b10000 #
#50
b101 !
b101 $
b100000 "
b100000 #
#60
b110 !
b110 $
b1000000 "
b1000000 #
#70
b111 !
b111 $
b10000000 "
b10000000 #
